PowerBlur/__init__.py
PowerBlur/power_blur.py
powerblur-0.1.2.dist-info/licenses/LICENSE
powerblur-0.1.2.dist-info/licenses/NOTICE
powerblur-0.1.2.dist-info/METADATA
powerblur-0.1.2.dist-info/WHEEL
powerblur-0.1.2.dist-info/top_level.txt
powerblur-0.1.2.dist-info/RECORD
