Metadata-Version: 2.4
Name: PowerBlur
Version: 0.1.2
Summary: PowerBlur is an image blur processing tool based on Pillow...
Author-email: 校溯 <xiaosu-1009@qq.com>, 徐付豫 <xufuyu-mg@outlook.com>
License:                                  Apache License
Project-URL: Homepage, https://github.com/xiaosuyyds/PowerBlur/
Keywords: blur,image-processing,pillow
Classifier: Programming Language :: Python :: 3
Classifier: License :: OSI Approved :: Apache Software License
Classifier: Operating System :: OS Independent
Requires-Python: >=3.0
License-File: LICENSE
License-File: NOTICE
Requires-Dist: Pillow
Requires-Dist: numpy
Dynamic: license-file
